hatch_uv/__about__.py
hatch_uv/__init__.py
hatch_uv/hooks.py
hatch_uv/plugin.py
hatch_uv-0.0.5.dist-info/METADATA
hatch_uv-0.0.5.dist-info/WHEEL
hatch_uv-0.0.5.dist-info/entry_points.txt
hatch_uv-0.0.5.dist-info/licenses/LICENSE.txt
hatch_uv-0.0.5.dist-info/RECORD
